{"Sports": "#222034", "Fiction Park": "#45283c", "Money": "#663931", "Video": "#8f563b", "Blog": "#df7126", "Int'l Coverage": "#d9a066", "Photo-feature": "#eec39a", "Escalate": "#fbf236", "Health & Style": "#99e550", "Saturday Features": "#6abe30", "Oped": "#37946e", "INTERVIEW": "#4b692f", "Entertainment": "#524b24", "News Makers 2017": "#323c39", "Editorial": "#3f3f74", "Capital": "#306082", "news": "#5b6ee1", "General": "#639bff", "National": "#5fcde4", "World": "#cbdbfc", "SILVER LININGS": "#ffffff"}